bqskit/setup.py
bqskit/bqskit/__init__.py
bqskit/bqskit/synthesis.py
qfast/__init__.py
qfast/__main__.py
qfast/gate.py
qfast/pauli.py
qfast/perm.py
qfast/plugins.py
qfast/synthesis.py
qfast/topology.py
qfast/utils.py
qfast/decomposition/__init__.py
qfast/decomposition/circuitmodel.py
qfast/decomposition/decomposer.py
qfast/decomposition/gatemodel.py
qfast/decomposition/optimizer.py
qfast/decomposition/models/fixedmodel.py
qfast/decomposition/models/perm/__init__.py
qfast/decomposition/models/perm/fixedgate.py
qfast/decomposition/models/perm/genericgate.py
qfast/decomposition/models/perm/permmodel.py
qfast/decomposition/models/softpauli/__init__.py
qfast/decomposition/models/softpauli/fixedgate.py
qfast/decomposition/models/softpauli/genericgate.py
qfast/decomposition/models/softpauli/softpaulimodel.py
qfast/decomposition/optimizers/lbfgs.py
qfast/instantiation/__init__.py
qfast/instantiation/instantiater.py
qfast/instantiation/nativetool.py
qfast/instantiation/native/qs.py
qfast/recombination/__init__.py
qfast/recombination/combiner.py
qfast/recombination/combiners/naive.py
qfast-2.2.0.dist-info/LICENSE.txt
qfast-2.2.0.dist-info/METADATA
qfast-2.2.0.dist-info/WHEEL
qfast-2.2.0.dist-info/top_level.txt
qfast-2.2.0.dist-info/RECORD
