Metadata-Version: 2.1
Name: qfast
Version: 2.2.0
Summary: Quantum Fast Approximate Synthesis Tool
Home-page: https://github.com/BQSKit/qfast
Author: Ed Younis
Author-email: edyounis@lbl.gov
License: UNKNOWN
Project-URL: Bug Tracker, https://github.com/BQSKit/qfast/issues
Project-URL: Source Code, https://github.com/BQSKit/qfast
Keywords: quantum synthesis compilation
Platform: UNKNOWN
Classifier: Development Status :: 5 - Production/Stable
Classifier: Environment :: Console
Classifier: Intended Audience :: Developers
Classifier: Intended Audience :: Science/Research
Classifier: Operating System :: OS Independent
Classifier: Programming Language :: Python :: 3 :: Only
Classifier: Programming Language :: Python :: 3.5
Classifier: Programming Language :: Python :: 3.6
Classifier: Programming Language :: Python :: 3.7
Classifier: Topic :: Scientific/Engineering
Classifier: Topic :: Scientific/Engineering :: Mathematics
Classifier: Topic :: Scientific/Engineering :: Physics
Classifier: Topic :: Software Development :: Compilers
Requires-Python: >=3.5, <4
Requires-Dist: numpy (>=1.16.6)
Requires-Dist: scipy (>=1.4.1)
Requires-Dist: sympy (>=1.5)
Requires-Dist: qsearch (>=2.4.0)
